MANIFEST.in
README.txt
plonetheme.equipoteih-configure.zcml
setup.cfg
setup.py
docs/HISTORY.txt
docs/INSTALL.txt
docs/LICENSE.GPL
docs/LICENSE.txt
plonetheme/__init__.py
plonetheme.equipoteih.egg-info/PKG-INFO
plonetheme.equipoteih.egg-info/SOURCES.txt
plonetheme.equipoteih.egg-info/dependency_links.txt
plonetheme.equipoteih.egg-info/entry_points.txt
plonetheme.equipoteih.egg-info/namespace_packages.txt
plonetheme.equipoteih.egg-info/not-zip-safe
plonetheme.equipoteih.egg-info/requires.txt
plonetheme.equipoteih.egg-info/top_level.txt
plonetheme/equipoteih/__init__.py
plonetheme/equipoteih/configure.zcml
plonetheme/equipoteih/profiles.zcml
plonetheme/equipoteih/setuphandlers.py
plonetheme/equipoteih/skins.zcml
plonetheme/equipoteih/tests.py
plonetheme/equipoteih/version.txt
plonetheme/equipoteih/browser/__init__.py
plonetheme/equipoteih/browser/configure.zcml
plonetheme/equipoteih/browser/interfaces.py
plonetheme/equipoteih/browser/viewlet.pt
plonetheme/equipoteih/browser/viewlets.py
plonetheme/equipoteih/browser/images/README.txt
plonetheme/equipoteih/browser/stylesheets/README.txt
plonetheme/equipoteih/browser/stylesheets/main.css
plonetheme/equipoteih/profiles/default/cssregistry.xml
plonetheme/equipoteih/profiles/default/import_steps.xml
plonetheme/equipoteih/profiles/default/jsregistry.xml
plonetheme/equipoteih/profiles/default/metadata.xml
plonetheme/equipoteih/profiles/default/plonetheme.equipoteih_various.txt
plonetheme/equipoteih/profiles/default/skins.xml
plonetheme/equipoteih/profiles/default/viewlets.xml
plonetheme/equipoteih/skins/plonetheme_equipoteih_custom_images/CONTENT.txt
plonetheme/equipoteih/skins/plonetheme_equipoteih_custom_images/logo.jpg
plonetheme/equipoteih/skins/plonetheme_equipoteih_custom_templates/CONTENT.txt
plonetheme/equipoteih/skins/plonetheme_equipoteih_styles/CONTENT.txt
plonetheme/equipoteih/skins/plonetheme_equipoteih_styles/base_properties.props
plonetheme/equipoteih/skins/plonetheme_equipoteih_styles/rcomstyles.css.dtml
plonetheme/equipoteih/skins/plonetheme_equipoteih_styles/rcomstyles_anon.css.dtml