Metadata-Version: 1.0
Name: plonetheme.equipoteih
Version: 1.0dev-r584
Summary: An installable theme for Plone 3.0
Home-page: http://www.rcom.com.ar/
Author: Rcom
Author-email: info@rcom.com.ar
License: GPL
Keywords: web zope plone theme
Platform: UNKNOWN
Classifier: Framework :: Plone
Classifier: Programming Language :: Python
Classifier: Topic :: Software Development :: Libraries :: Python Modules
